{"_type":"export","__export_format":4,"__export_date":"2023-08-21T22:58:40.330Z","__export_source":"insomnia.desktop.app:v2022.7.0","resources":[{"_id":"req_6797f87350714787a3e26b1be11cab99","parentId":"fld_1cc55dc536914ea3b605afa6ae6cce55","modified":1656461667435,"created":1656092909908,"url":"{{ _.Endpoints.AcquiringBankApi }}/api/account/v1","name":"AccountPaginated","description":"","method":"GET","body":{},"parameters":[{"id":"pair_43579bee3cf94d80a694a55fa8dc2416","name":"pageNumber","value":"1","description":""},{"id":"pair_f520fb7862694e76bdcdcbbc6ca19203","name":"pageSize","value":"10","description":""}],"headers":[],"authentication":{},"metaSortKey":-1656092909908,"isPrivate":false,"settingStoreCookies":true,"settingSendCookies":true,"settingDisableRenderRequestBody":false,"settingEncodeUrl":true,"settingRebuildPath":true,"settingFollowRedirects":"global","_type":"request"},{"_id":"fld_1cc55dc536914ea3b605afa6ae6cce55","parentId":"fld_8e781c802deb4d44aa4749e73f4a0c35","modified":1656026352806,"created":1656026352806,"name":"Account","description":"","environment":{},"environmentPropertyOrder":null,"metaSortKey":-1656026352806,"_type":"request_group"},{"_id":"fld_8e781c802deb4d44aa4749e73f4a0c35","parentId":"wrk_7fcae653ecb54e1aabde20195b76cc03","modified":1656023390766,"created":1656023390766,"name":"AcquiringBankSimulator","description":"","environment":{},"environmentPropertyOrder":null,"metaSortKey":-1656023390766,"_type":"request_group"},{"_id":"wrk_7fcae653ecb54e1aabde20195b76cc03","parentId":null,"modified":1692658659521,"created":1656023363111,"name":"Acquiring Bank Simulator","description":"","scope":"collection","_type":"workspace"},{"_id":"req_8234f001ccef4d759420b9402dbd28fb","parentId":"fld_1cc55dc536914ea3b605afa6ae6cce55","modified":1656540353018,"created":1656026364181,"url":"{{ _.Endpoints.AcquiringBankApi }}/api/account/v1","name":"AccountCreate","description":"","method":"POST","body":{"mimeType":"application/json","text":"{\n\t\"clientName\": \"Icaro Sousa\"\n}"},"parameters":[],"headers":[{"name":"Content-Type","value":"application/json","id":"pair_3829a0c40ac54d01be20304ce9e60b02"}],"authentication":{},"metaSortKey":-1656026364181,"isPrivate":false,"settingStoreCookies":true,"settingSendCookies":true,"settingDisableRenderRequestBody":false,"settingEncodeUrl":true,"settingRebuildPath":true,"settingFollowRedirects":"global","_type":"request"},{"_id":"req_a9d4052b4635479d81150b1e1bf9d38f","parentId":"fld_a29e2a47d50b4469b9426aaf191509dc","modified":1656535505441,"created":1656025856233,"url":"{{ _.Endpoints.AcquiringBankApi }}/api/Payment/v1","name":"ProcessTransaction","description":"","method":"POST","body":{"mimeType":"application/json","text":"{\n\t\"cardDetails\": {\n\t\t\"number\": \"{% response 'body', 'req_df4a88ba119343f3a8ef60657dc6b54e', 'b64::JC5pdGVtc1swXS5udW1iZXI=::46b', 'always', 60 %}\",\n\t\t\"verificationValue\": \"{% response 'body', 'req_df4a88ba119343f3a8ef60657dc6b54e', 'b64::JC5pdGVtc1swXS52ZXJpZmljYXRpb25WYWx1ZQ==::46b', 'never', 60 %}\",\n\t\t\"clientName\": \"{% response 'body', 'req_df4a88ba119343f3a8ef60657dc6b54e', 'b64::JC5pdGVtc1swXS5jbGllbnROYW1l::46b', 'never', 60 %}\",\n\t\t\"expiresAt\": {\n\t\t\t\"year\": {% response 'body', 'req_df4a88ba119343f3a8ef60657dc6b54e', 'b64::JC5pdGVtc1swXS5leHBpcmVzQXQueWVhcg==::46b', 'never', 60 %},\n\t\t\t\"month\": {% response 'body', 'req_df4a88ba119343f3a8ef60657dc6b54e', 'b64::JC5pdGVtc1swXS5leHBpcmVzQXQubW9udGg=::46b', 'never', 60 %}\n\t\t}\n\t},\n\t\"details\": {\n\t\t\"amount\": 12.99,\n\t\t\"currency\": \"EUR\",\n\t\t\"merchant\": \"Dunkin\"\n\t}\n}"},"parameters":[],"headers":[{"name":"Content-Type","value":"application/json","id":"pair_be060185bedb434aaa58161f527a5b27"}],"authentication":{},"metaSortKey":-1656025856233,"isPrivate":false,"settingStoreCookies":true,"settingSendCookies":true,"settingDisableRenderRequestBody":false,"settingEncodeUrl":true,"settingRebuildPath":true,"settingFollowRedirects":"global","_type":"request"},{"_id":"fld_a29e2a47d50b4469b9426aaf191509dc","parentId":"fld_8e781c802deb4d44aa4749e73f4a0c35","modified":1656025417354,"created":1656025417354,"name":"Transactions","description":"","environment":{},"environmentPropertyOrder":null,"metaSortKey":-1656025417354,"_type":"request_group"},{"_id":"req_df4a88ba119343f3a8ef60657dc6b54e","parentId":"fld_78337ed37e444fd490067c975ac8ebfa","modified":1656529929108,"created":1656064678796,"url":"{{ _.Endpoints.AcquiringBankApi }}/api/card/v1/{% response 'body', 'req_6797f87350714787a3e26b1be11cab99', 'b64::JC5pdGVtc1swXS5hY2NvdW50SWQ=::46b', 'always', 60 %}","name":"CardsPaginatedByAccountId","description":"","method":"GET","body":{},"parameters":[{"id":"pair_e4a8a0105e6c49d1a01358f194bbfdc4","name":"pageNumber","value":"1","description":""},{"id":"pair_306fc947eb6746ff9e71de7b0bab6920","name":"pageSize","value":"10","description":""}],"headers":[],"authentication":{},"metaSortKey":-1656064678796,"isPrivate":false,"settingStoreCookies":true,"settingSendCookies":true,"settingDisableRenderRequestBody":false,"settingEncodeUrl":true,"settingRebuildPath":true,"settingFollowRedirects":"global","_type":"request"},{"_id":"fld_78337ed37e444fd490067c975ac8ebfa","parentId":"fld_8e781c802deb4d44aa4749e73f4a0c35","modified":1656025394450,"created":1656025394450,"name":"Cards","description":"","environment":{},"environmentPropertyOrder":null,"metaSortKey":-1656025394450,"_type":"request_group"},{"_id":"req_774bb586307b4c8a84361a650a6aa9a2","parentId":"fld_78337ed37e444fd490067c975ac8ebfa","modified":1656530127767,"created":1656026055416,"url":"{{ _.Endpoints.AcquiringBankApi }}/api/card/v1/{% response 'body', 'req_df4a88ba119343f3a8ef60657dc6b54e', 'b64::JC5pdGVtc1swXS5pZA==::46b', 'always', 60 %}","name":"CardUpdate","description":"","method":"PATCH","body":{"mimeType":"application/json","text":"{\n\t\"limit\": 4000,\n\t\"active\": true\n}"},"parameters":[],"headers":[{"name":"Content-Type","value":"application/json","id":"pair_b3144b2d28014838ac59f36cfcb881cb"}],"authentication":{},"metaSortKey":-1656026055416,"isPrivate":false,"settingStoreCookies":true,"settingSendCookies":true,"settingDisableRenderRequestBody":false,"settingEncodeUrl":true,"settingRebuildPath":true,"settingFollowRedirects":"global","_type":"request"},{"_id":"req_e2adad6f06b14972aae47a6ce2bd05ce","parentId":"fld_78337ed37e444fd490067c975ac8ebfa","modified":1656530126926,"created":1656026024943,"url":"{{ _.Endpoints.AcquiringBankApi }}/api/card/v1/{% response 'body', 'req_df4a88ba119343f3a8ef60657dc6b54e', 'b64::JC5pdGVtc1swXS5pZA==::46b', 'always', 60 %}","name":"CardDeletion","description":"","method":"DELETE","body":{},"parameters":[],"headers":[],"authentication":{},"metaSortKey":-1656026024943,"isPrivate":false,"settingStoreCookies":true,"settingSendCookies":true,"settingDisableRenderRequestBody":false,"settingEncodeUrl":true,"settingRebuildPath":true,"settingFollowRedirects":"global","_type":"request"},{"_id":"req_9da82ed28594454dbead5af88909fe4a","parentId":"fld_78337ed37e444fd490067c975ac8ebfa","modified":1656540359140,"created":1656025442032,"url":"{{ _.Endpoints.AcquiringBankApi }}/api/card/v1/","name":"CardCreation","description":"","method":"POST","body":{"mimeType":"application/json","text":"{\n\t\"accountId\": \"{% response 'body', 'req_6797f87350714787a3e26b1be11cab99', 'b64::JC5pdGVtc1swXS5hY2NvdW50SWQ=::46b', 'always', 60 %}\",\n\t\"limit\": 200,\n\t\"active\": true\n}"},"parameters":[],"headers":[{"name":"Content-Type","value":"application/json","id":"pair_25c0cfcfdb5d4dbebd6675628c5cab14"}],"authentication":{},"metaSortKey":-1656025442032,"isPrivate":false,"settingStoreCookies":true,"settingSendCookies":true,"settingDisableRenderRequestBody":false,"settingEncodeUrl":true,"settingRebuildPath":true,"settingFollowRedirects":"global","_type":"request"},{"_id":"env_322b9e2c5d381b14a8fbe95804cf957c399fd6d4","parentId":"wrk_7fcae653ecb54e1aabde20195b76cc03","modified":1656458197018,"created":1656023363112,"name":"Base Environment","data":{},"dataPropertyOrder":{},"color":null,"isPrivate":false,"metaSortKey":1656023363112,"_type":"environment"},{"_id":"jar_7f1298b4ea1b5bd0b279679b4fa19deb86fa6623","parentId":"wrk_7fcae653ecb54e1aabde20195b76cc03","modified":1656023363113,"created":1656023363113,"name":"Default Jar","cookies":[],"_type":"cookie_jar"},{"_id":"spc_ef1c2a6993dd41b080cc4d585657fcc9","parentId":"wrk_7fcae653ecb54e1aabde20195b76cc03","modified":1656023363111,"created":1656023363111,"fileName":"Checkout.com","contents":"","contentType":"yaml","_type":"api_spec"},{"_id":"env_2202a507b24b4a47a56568e615397a39","parentId":"env_322b9e2c5d381b14a8fbe95804cf957c399fd6d4","modified":1656536263257,"created":1656458201983,"name":"CheckoutEnvironment","data":{"Endpoints":{"AcquiringBankApi":"http://localhost:5000","PaymentGatewayApi":"http://localhost:5001"}},"dataPropertyOrder":{"&":["Endpoints"],"&~|Endpoints":["AcquiringBankApi","PaymentGatewayApi"]},"color":null,"isPrivate":false,"metaSortKey":1656458201983,"_type":"environment"}]}